get_user_headers.py
get_user_headers-0.1.2.dist-info/top_level.txt
get_user_headers-0.1.2.dist-info/DESCRIPTION.rst
get_user_headers-0.1.2.dist-info/zip-safe
get_user_headers-0.1.2.dist-info/WHEEL
get_user_headers-0.1.2.dist-info/pbr.json
get_user_headers-0.1.2.dist-info/metadata.json
get_user_headers-0.1.2.dist-info/METADATA
get_user_headers-0.1.2.dist-info/RECORD
