Metadata-Version: 2.0
Name: get-user-headers
Version: 0.1.2
Summary: Helper for retrieving identifying headers from the user'sdefault browser
Home-page: https://github.com/ssokolow/get_user_headers
Author: Stephan Sokolow
Author-email: http://www.ssokolow.com/ContactMe
License: MIT
Keywords: http web bot spider automation
Platform: UNKNOWN
Classifier: Development Status :: 4 - Beta
Classifier: Intended Audience :: Developers
Classifier: License :: OSI Approved :: MIT License
Classifier: Operating System :: OS Independent
Classifier: Programming Language :: Python :: 2.7
Classifier: Programming Language :: Python :: 3
Classifier: Topic :: Internet :: WWW/HTTP
Classifier: Topic :: Software Development :: Libraries :: Python Modules
